olass/__init__.py
olass/config.py
olass/olass_client.py
olass/rules.py
olass/run.py
olass/utils.py
olass/version.py
olass/models/base.py
olass/models/base_query.py
olass/models/crud_mixin.py
olass/models/pagination.py
olass/models/patient.py
olass-0.0.3.dist-info/DESCRIPTION.rst
olass-0.0.3.dist-info/METADATA
olass-0.0.3.dist-info/RECORD
olass-0.0.3.dist-info/WHEEL
olass-0.0.3.dist-info/entry_points.txt
olass-0.0.3.dist-info/metadata.json
olass-0.0.3.dist-info/top_level.txt
