Metadata-Version: 2.0
Name: olass
Version: 0.0.3
Summary: OneFlorida Linkage Submission System
Home-page: https://github.com/ufbmi/olass-client
Author: Andrei Sura
Author-email: bmi-developers@ad.ufl.edu
License: MIT
Keywords: entity resolution,deduplication,record linkage
Platform: any
Classifier: Development Status :: 4 - Beta
Classifier: Environment :: Console
Classifier: Intended Audience :: Science/Research
Classifier: License :: OSI Approved :: MIT License
Classifier: Operating System :: MacOS :: MacOS X
Classifier: Operating System :: Microsoft :: Windows
Classifier: Operating System :: POSIX
Classifier: Operating System :: Unix
Classifier: Programming Language :: Python :: 3.4
Classifier: Programming Language :: Python :: 3.5
Classifier: Topic :: Scientific/Engineering :: Medical Science Apps.
Requires-Dist: SQLAlchemy (==1.0.14)
Requires-Dist: invoke (==0.13.0)
Requires-Dist: mock (==2.0.0)
Requires-Dist: mysql-connector (==2.1.3)
Requires-Dist: pylint (==1.6.4)
Requires-Dist: pytest-cov (==2.3.1)
Requires-Dist: requests (==2.11.0)
Requires-Dist: requests-oauthlib (==0.6.2)
Requires-Dist: setuptools-scm (==1.11.1)
